uavcan/__init__.py
uavcan/version.py
uavcan-1.0.0.dev34.dist-info/LICENSE
uavcan-1.0.0.dev34.dist-info/METADATA
uavcan-1.0.0.dev34.dist-info/WHEEL
uavcan-1.0.0.dev34.dist-info/top_level.txt
uavcan-1.0.0.dev34.dist-info/RECORD
