Metadata-Version: 2.1
Name: uavcan
Version: 1.0.0.dev34
Summary: OBSOLETE, use pyuavcan_v0 instead
Home-page: http://uavcan.org
Author: Pavel Kirienko, Ben Dyer
Author-email: maintainers@uavcan.org
License: MIT
Platform: UNKNOWN
License-File: LICENSE
